scithermo/__init__.py
scithermo/antoine.py
scithermo/chem_constants.py
scithermo/cp_ig.csv
scithermo/cp_ig.py
scithermo/critical_constants.csv
scithermo/critical_constants.py
scithermo/util.py
SciThermo-0.0.1.dist-info/METADATA
SciThermo-0.0.1.dist-info/WHEEL
SciThermo-0.0.1.dist-info/top_level.txt
SciThermo-0.0.1.dist-info/RECORD
